pypipegzip/__init__.py
pypipegzip/pypipegzip.py
pypipegzip/static.py
pypipegzip-0.0.24.dist-info/LICENSE
pypipegzip-0.0.24.dist-info/METADATA
pypipegzip-0.0.24.dist-info/WHEEL
pypipegzip-0.0.24.dist-info/top_level.txt
pypipegzip-0.0.24.dist-info/RECORD
