Metadata-Version: 2.1
Name: pypipegzip
Version: 0.0.24
Summary: faster read of gzip files using a pipe to zcat(1)
Home-page: https://veltzer.github.io/pypipegzip
Download-URL: https://github.com/veltzer/pypipegzip
Author: Mark Veltzer
Author-email: mark.veltzer@gmail.com
Maintainer: Mark Veltzer
Maintainer-email: mark.veltzer@gmail.com
License: MIT
Keywords: pipe,pipeline,gzip,read,speed,pypipegzip
Platform: python3
Classifier: Development Status :: 4 - Beta
Classifier: Environment :: Console
Classifier: Operating System :: OS Independent
Classifier: Programming Language :: Python
Classifier: Programming Language :: Python :: 3
Classifier: Programming Language :: Python :: 3 :: Only
Classifier: Programming Language :: Python :: 3.11
Classifier: Topic :: Utilities
Classifier: License :: OSI Approved :: MIT License
License-File: LICENSE
